Workbook

Sheet IS
B2: POPEES BABY CARE PRODUCTS LIMITED
B3: STATEMENT OF COMPREHENSIVE INCOME | C3: PROVISIONAL | D3: PROJECTED | E3: PROJECTED | F3: PROJECTED | G3: PROJECTED | H3: PROJECTED
B4: Particulars | C4: 46112 | D4: 46477 | E4: 46843 | F4: 47208 | G4: 47573 | H4: 47938
B6: Revenue from operations | C6: =Notes!C9 -> 1.6200314e+09 | D6: =Notes!D9 -> 2.3617717e+09 | E6: =Notes!E9 -> 3.3113857e+09 | F6: =Notes!F9 -> 5.4104731e+09 | G6: =Notes!G9 -> 9.331984e+09 | H6: =Notes!H9 -> 1.166498e+10
B7: Other Income | C7: =Notes!C20 -> 4011740 | D7: =Notes!D20 -> 7987554.3 | E7: =Notes!E20 -> 9156658.1 | F7: =Notes!F20 -> 11305564 | G7: =Notes!G20 -> 12459609 | H7: =Notes!H20 -> 13619151
B9: Total Income (I+II) | C9: =SUM(C6:C7) -> 1.6240431e+09 | D9: =SUM(D6:D7) -> 2.3697593e+09 | E9: =SUM(E6:E7) -> 3.3205424e+09 | F9: =SUM(F6:F7) -> 5.4217787e+09 | G9: =SUM(G6:G7) -> 9.3444436e+09 | H9: =SUM(H6:H7) -> 1.1678599e+10
B11: Expenses
B12: Cost of Goods Sold | C12: =Notes!C29 -> 1.0789792e+09 | D12: =Notes!D29 -> 1.0225707e+09 | E12: =Notes!E29 -> 1.6116514e+09 | F12: =Notes!F29 -> 2.6976619e+09 | G12: =Notes!G29 -> 4.1881944e+09 | H12: =Notes!H29 -> 5.3927203e+09
B13: Employee benefits expenses | C13: =Notes!C38 -> 96252142 | D13: =Notes!D38 -> 1.959297e+08 | E13: =Notes!E38 -> 2.129297e+08 | F13: =Notes!F38 -> 2.2357619e+08 | G13: =Notes!G38 -> 2.34755e+08 | H13: =Notes!H38 -> 2.4649275e+08
B14: Finance costs | C14: 49550008 | D14: ='EMI SCHEDULE KOTAK'!C74 -> 39745847 | E14: ='EMI SCHEDULE KOTAK'!D74 -> 38683493 | F14: ='EMI SCHEDULE KOTAK'!E74 -> 36596332 | G14: ='EMI SCHEDULE KOTAK'!F74 -> 35347439 | H14: ='EMI SCHEDULE KOTAK'!G74 -> 33952461
B15: Depreciation and amortisation expenses | C15: 13779669 | D15: 20669504 | E15: 31004256 | F15: 46506384 | G15: 69759576 | H15: 1.0463936e+08
B16: Other expenses | C16: =Notes!C73 -> 1.492232e+08 | D16: =Notes!D73 -> 7.192708e+08 | E16: =Notes!E73 -> 8.6835508e+08 | F16: =Notes!F73 -> 1.1749078e+09 | G16: =Notes!G73 -> 1.7305315e+09 | H16: =Notes!H73 -> 2.0710484e+09
B18: Total Expenses | C18: =SUM(C12:C16) -> 1.3877842e+09 | D18: =SUM(D12:D16) -> 1.9981865e+09 | E18: =SUM(E12:E16) -> 2.7626239e+09 | F18: =SUM(F12:F16) -> 4.1792486e+09 | G18: =SUM(G12:G16) -> 6.2585879e+09 | H18: =SUM(H12:H16) -> 7.8488532e+09
B20: Profit before exceptional and extraordinary iteam and tax | C20: =C9-C18 -> 2.3625892e+08 | D20: =D9-D18 -> 3.7157276e+08 | E20: =E9-E18 -> 5.5791841e+08 | F20: =F9-F18 -> 1.2425301e+09 | G20: =G9-G18 -> 3.0858557e+09 | H20: =H9-H18 -> 3.829746e+09
B22: Exceptional Iteams | C22: 0 | D22: 0
C23: =C21/C6 -> 0 | D23: =D21/D6 -> 0 | E23: =E21/E6 -> 0 | F23: =F21/F6 -> 0 | G23: =G21/G6 -> 0 | H23: =H21/H6 -> 0
B24: Profit before extraordinary iteam and tax | C24: =C20-C22 -> 2.3625892e+08 | D24: =D20-D22 -> 3.7157276e+08 | E24: =E20-E22 -> 5.5791841e+08 | F24: =F20-F22 -> 1.2425301e+09 | G24: =G20-G22 -> 3.0858557e+09 | H24: =H20-H22 -> 3.829746e+09
B26: Extraordinary Iteams | C26: 0 | D26: 0
B28: Profit before Tax | C28: =C24-C26 -> 2.3625892e+08 | D28: =D24-D26 -> 3.7157276e+08 | E28: =E24-E26 -> 5.5791841e+08 | F28: =F24-F26 -> 1.2425301e+09 | G28: =G24-G26 -> 3.0858557e+09 | H28: =H24-H26 -> 3.829746e+09
B31: Tax Expense:
B32: (a) Current tax expense | C32: =C28*0.225 -> 53158258 | D32: =D28*0.225 -> 83603871 | E32: =E28*0.225 -> 1.2553164e+08 | F32: =F28*0.225 -> 2.7956927e+08 | G32: =G28*0.225 -> 6.9431753e+08 | H32: =H28*0.225 -> 8.6169284e+08
B33: (b) Prior year tax adjustments | C33: 0
B34: (c) Deferred tax | C34: 0 | D34: 0
B36: Profit / (Loss) for the period from continuing operations | C36: =C28-C32-C34-C33 -> 1.8310067e+08 | D36: =D28-D32-D34-D33 -> 2.8796889e+08 | E36: =E28-E32-E34-E33 -> 4.3238677e+08 | F36: =F28-F32-F34-F33 -> 9.629608e+08 | G36: =G28-G32-G34-G33 -> 2.3915381e+09 | H36: =H28-H32-H34-H33 -> 2.9680531e+09
B37: Profit / (Loss) from discontinuing operations | C37: 0 | D37: 0
B38: Tax from discontinuing operations | C38: 0 | D38: 0
B39: Profit/ (Loss) from discontinuing operations | C39: 0 | D39: 0
B41: Profit/(Loss) for the Period | C41: =C36+C37+C38+C39 -> 1.8310067e+08 | D41: =D36+D37+D38+D39 -> 2.8796889e+08 | E41: =E36+E37+E38+E39 -> 4.3238677e+08 | F41: =F36+F37+F38+F39 -> 9.629608e+08 | G41: =G36+G37+G38+G39 -> 2.3915381e+09 | H41: =H36+H37+H38+H39 -> 2.9680531e+09
B43: Earning per equity share:
B44: (1) Basic | C44: =C41/(BS!C8/10) -> 8.4881955 | D44: =D41/(BS!D8/10) -> 12.715513 | E44: =E41/(BS!E8/10) -> 19.092408 | F44: =F41/(BS!F8/10) -> 42.520358 | G44: =G41/(BS!G8/10) -> 105.60041 | H44: =H41/(BS!H8/10) -> 131.05692
B45: (2) Diluted | C45: =C44 -> 8.4881955 | D45: =D44 -> 12.715513 | E45: =E44 -> 19.092408 | F45: =F44 -> 42.520358 | G45: =G44 -> 105.60041 | H45: =H44 -> 131.05692

Sheet BS
B2: POPEES BABY CARE PRODUCTS LIMITED
B3: STATEMENT OF FINANCIAL POSITION | C3: PROVISIONAL | D3: PROJECTED | E3: PROJECTED | F3: PROJECTED | G3: PROJECTED | H3: PROJECTED
B4: Particulars | C4: 46112 | D4: 46477 | E4: 46843 | F4: 47208 | G4: 47573 | H4: 47938
B5: EQUITY AND LIABILITIES
B7: Shareholders’ funds
B8: (a) Share capital | C8: 215712120 | D8: =C8+10758410 -> 226470530 | E8: =D8 -> 226470530 | F8: =E8 -> 226470530 | G8: =F8 -> 226470530 | H8: =G8 -> 226470530
B9: (b) Reserves and surplus | C9: =Notes!C91 -> 8.2581804e+08 | D9: =Notes!D91 -> 1.2644047e+09 | E9: =Notes!E91 -> 1.6967914e+09 | F9: =Notes!F91 -> 2.6597522e+09 | G9: =Notes!G91 -> 5.0512904e+09 | H9: =Notes!H91 -> 8.0193435e+09
B10: Share application money pending allotments
B11: Non-current liabilities
B12: (a) Long-term borrowings | C12: 32690547 | D12: ='EMI SCHEDULE KOTAK'!C75 -> 57315522 | E12: ='EMI SCHEDULE KOTAK'!D75 -> 35363372 | F12: ='EMI SCHEDULE KOTAK'!E75 -> 24494647 | G12: ='EMI SCHEDULE KOTAK'!F75 -> 13495417 | H12: ='EMI SCHEDULE KOTAK'!G75 -> 1101210
B13: (b) Deferred tax liabilities (net)
B14: (c) Other Long Term Liabilities | C14: =Notes!C113 -> 1.1190467e+08 | D14: =Notes!D113 -> 1.6190467e+08 | E14: =Notes!E113 -> 2.1190467e+08 | F14: =Notes!F113 -> 2.6190467e+08 | G14: =Notes!G113 -> 3.1190467e+08 | H14: =Notes!H113 -> 3.6190467e+08
B15: (d) Long term provision
B16: Current liabilities
B17: (a) Short Term Borrowings | C17: =Notes!C133 -> 2.067451e+08 | D17: =Notes!D133-300000000 -> 25000000 | E17: =Notes!E133-250000000 -> 25000000 | F17: =Notes!F133-250000000 -> 25000000 | G17: =Notes!G133-250000000 -> 25000000 | H17: =Notes!H133-250000000 -> 25000000
B18: (b) Trade payables
B19: (A) total outstanding dues of micro enterprises and small enterprises | C19: 0 | D19: 0
B20: (B) total outstanding dues of Creditors other than micro enterprises and small enterprises | C20: 2.2217463e+08 | D20: =Notes!D24*0.1 -> 84569884 | E20: =Notes!E24*0.1 -> 1.387582e+08 | F20: =Notes!F24*0.1 -> 2.4222089e+08 | G20: =Notes!G24*0.1 -> 3.8389498e+08 | H20: =Notes!H24*0.1 -> 4.978258e+08
B21: (c) Other current liabilities | C21: =Notes!C157 -> 94131526 | D21: =Notes!D157 -> 83566996 | E21: =Notes!E157 -> 97215399 | F21: =Notes!F157 -> 1.1181925e+08 | G21: =Notes!G157 -> 1.278983e+08 | H21: =Notes!H157 -> 1.4403502e+08
B22: (d) Short-term provisions | C22: =Notes!C167 -> 53158258 | D22: =Notes!D167 -> 83603871 | E22: =Notes!E167 -> 1.2553164e+08 | F22: =Notes!F167 -> 2.7956927e+08 | G22: =Notes!G167 -> 6.9431753e+08 | H22: =Notes!H167 -> 8.6169284e+08
B24: TOTAL | C24: =SUM(C7:C23) -> 1.7623349e+09 | D24: =SUM(D7:D22) -> 1.9868361e+09 | E24: =SUM(E7:E22) -> 2.5570353e+09 | F24: =SUM(F7:F22) -> 3.8312315e+09 | G24: =SUM(G7:G22) -> 6.8342718e+09 | H24: =SUM(H7:H22) -> 1.0137374e+10
B25: ASSETS
B27: Non-current assets
B28: (a) (i) Property, Plant and Equipment | C28: 1.2332646e+08 | D28: =184989692.46+150000000 -> 3.3498969e+08 | E28: =277484538.69+150000000 -> 4.2748454e+08 | F28: =416226808.035+150000000 -> 5.6622681e+08 | G28: =624340212.0525+150000000 -> 7.7434021e+08 | H28: =936510318.07875+150000000 -> 1.0865103e+09
B29: (ii) Intangible assets | C29: 45721641 | D29: 44403127 | E29: 60996576 | F29: 83790996 | G29: 1.1510369e+08 | H29: 1.5811794e+08
B30: (iii) Capital Work in progress | C30: 0 | D30: 0
B31: (iv) Intangible Assets under Development | C31: 0 | D31: 0
B32: (b) Non-current investments | C32: 0 | D32: 0
B33: (c) Deferred Tax Assets | C33: 6008732.5 | D33: =D28*0.048722 -> 16321368 | E33: =E28*0.048722 -> 20827902 | F33: =F28*0.048722 -> 27587703 | G33: =G28*0.048722 -> 37727404 | H33: =H28*0.048722 -> 52936956
B34: (d) Long term Loans and Advances | C34: 0 | D34: 0
B35: (e) Other Non Current Assets | C35: =Notes!C193 -> 34042609 | D35: =Notes!D193 -> 62399357 | E35: =Notes!E193 -> 85445338 | F35: =Notes!F193 -> 1.0849987e+08 | G35: =Notes!G193 -> 1.3156338e+08 | H35: =Notes!H193 -> 1.5463631e+08
B36: Current assets
B37: (a) Current Investments | C37: 0 | D37: 0
B38: (b) Inventories | C38: =Notes!C207 -> 7.9253648e+08 | D38: =Notes!D207 -> 8.9094417e+08 | E38: =Notes!E207 -> 1.2437544e+09 | F38: =Notes!F207 -> 1.6611853e+09 | G38: =Notes!G207 -> 2.1422994e+09 | H38: =Notes!H207 -> 2.5771765e+09
B39: (c) Trade receivables | C39: 4.2913483e+08 | D39: =(IS!D6*40%)/12*3 -> 2.3617717e+08 | E39: =(IS!E6*40%)/12*3 -> 331138570 | F39: =(IS!F6*40%)/12*3 -> 5.4104731e+08 | G39: =(IS!G6*40%)/12*3 -> 9.331984e+08 | H39: =(IS!H6*40%)/12*3 -> 1.166498e+09
B40: (d) Cash and cash equivalents | C40: =Notes!C217 -> 6136348.2 | D40: =Notes!D217 -> 2.3215405e+08 | E40: =Notes!E217 -> 1.7846036e+08 | F40: =Notes!F217 -> 5.938611e+08 | G40: =Notes!G217 -> 2.4101353e+09 | H40: =Notes!H217 -> 4.6097777e+09
B41: (e) Short-term loans and advances | C41: =Notes!C231 -> 96618755 | D41: =Notes!D231 -> 69384705 | E41: =Notes!E231 -> 1.0886505e+08 | F41: =Notes!F231 -> 1.4896987e+08 | G41: =Notes!G231 -> 1.8984158e+08 | H41: =Notes!H231 -> 2.3165737e+08
B42: (f) Other Current Assets | C42: =Notes!C237 -> 2.2880904e+08 | D42: =Notes!D237 -> 100062500 | E42: =Notes!E237 -> 100062500 | F42: =Notes!F237 -> 100062500 | G42: =Notes!G237 -> 100062500 | H42: =Notes!H237 -> 100062500
B43: TOTAL | C43: =SUM(C28:C42) -> 1.7623349e+09 | D43: =SUM(D28:D42) -> 1.9868361e+09 | E43: =SUM(E28:E42) -> 2.5570353e+09 | F43: =SUM(F28:F42) -> 3.8312315e+09 | G43: =SUM(G28:G42) -> 6.8342718e+09 | H43: =SUM(H28:H42) -> 1.0137374e+10
D44: =D24-D43 -> 0 | E44: =E24-E43 -> 0 | F44: =F24-F43 -> 0 | G44: =G24-G43 -> 0 | H44: =H24-H43 -> 0

Sheet CFS
B1: =[1]BS!$A$1 -> POPEES BABY CARE PRODUCTS PRIVATE LIMITED
B2: =[1]BS!$A$2 -> CIN: U51900KL2016PTC045955
B3: =[1]BS!$A$3 -> No.II/122 B, Pathiriyal, Malappuram, Kerala 676123
B5: Cash Flow Statement for the year ended
B6: Particulars | C6: For the year ended 31 Mar 2026 | D6: For the year ended 31 Mar 2027 | E6: For the year ended 31 Mar 2028 | F6: For the year ended 31 Mar 2029 | G6: For the year ended 31 Mar 2030
B7: CASH FLOW FROM OPERATING ACTIVITIES
B8: Net Profit/(Loss) Before Taxation | C8: =IS!C20 -> 2.3625892e+08 | D8: =IS!D20 -> 3.7157276e+08 | E8: =IS!E20 -> 5.5791841e+08 | F8: =IS!F20 -> 1.2425301e+09 | G8: =IS!G20 -> 3.0858557e+09
B9: Adjustments For
B10: Depreciation | C10: =IS!C15 -> 13779669 | D10: =IS!D15 -> 20669504 | E10: =IS!E15 -> 31004256 | F10: =IS!F15 -> 46506384 | G10: =IS!G15 -> 69759576
B11: (Profit)/Loss On Sale Of Assets
B12: Deferred revenue expenditure
B13: Interest And Finance Charge | C13: =IS!C14 -> 49550008 | D13: =IS!D14 -> 39745847 | E13: =IS!E14 -> 38683493 | F13: =IS!F14 -> 36596332 | G13: =IS!G14 -> 35347439
B14: Operating Profit Before Working Capital Changes | C14: =SUM(C8:C13) -> 2.995886e+08 | D14: =SUM(D8:D13) -> 4.3198811e+08 | E14: =SUM(E8:E13) -> 6.2760616e+08 | F14: =SUM(F8:F13) -> 1.3256328e+09 | G14: =SUM(G8:G13) -> 3.1909627e+09
B15: Adjustments For Working Capital Changes
B16: Inventories | C16: =[2]BS!$D$41-BS!C38 -> -3.1189854e+08 | D16: =BS!C38-BS!D38 -> -98407693 | E16: =BS!D38-BS!E38 -> -3.5281025e+08 | F16: =BS!E38-BS!F38 -> -4.1743092e+08 | G16: =BS!F38-BS!G38 -> -4.8111405e+08
B17: Loans and advances
B18: Other Non Current Assets | C18: =([2]BS!$D$38+4333903.89+[2]BS!$D$36)-BS!C35+BS!C33 -> 18571007 | D18: =(BS!C35+BS!C33)-(BS!D35+BS!D33) -> -38669383 | E18: =(BS!D35+BS!D33)-(BS!E35+BS!E33) -> -27552515 | F18: =(BS!E35+BS!E33)-(BS!F35+BS!F33) -> -29814331 | G18: =(BS!F35+BS!F33)-(BS!G35+BS!G33) -> -33203208
B19: Other current assets | C19: =+[2]BS!$D$45-BS!C42 -> 1.700141e+08 | D19: =BS!C42-BS!D42 -> 1.2874654e+08 | E19: =BS!D42-BS!E42 -> 0 | F19: =BS!E42-BS!F42 -> 0 | G19: =BS!F42-BS!G42 -> 0
B20: Other Long Term Liabilities | C20: =BS!C14-[2]BS!$D$17 -> -9568890 | D20: =BS!D14-BS!C14 -> 50000000 | E20: =BS!E14-BS!D14 -> 50000000 | F20: =BS!F14-BS!E14 -> 50000000 | G20: =BS!G14-BS!F14 -> 50000000
B21: Other current liabilities | C21: =BS!C21-[2]BS!$D$24 -> -19744943 | D21: =BS!D21-BS!C21 -> -10564530 | E21: =BS!E21-BS!D21 -> 13648403 | F21: =BS!F21-BS!E21 -> 14603851 | G21: =BS!G21-BS!F21 -> 16079050
B22: Short term borrowings | C22: =BS!C17-[2]BS!$D$20 -> 2610681.2 | D22: =BS!D17-BS!C17 -> -1.817451e+08 | E22: =BS!E17-BS!D17 -> 0 | F22: =BS!F17-BS!E17 -> 0 | G22: =BS!G17-BS!F17 -> 0
B23: Short-term loans and advances | C23: =[2]BS!$D$44-BS!C41 -> -64153904 | D23: =BS!C41-BS!D41 -> 27234050 | E23: =BS!D41-BS!E41 -> -39480346 | F23: =BS!E41-BS!F41 -> -40104818 | G23: =BS!F41-BS!G41 -> -40871707
B24: Short term provisions | C24: =BS!C22-[2]BS!$D$25 -> 22351865 | D24: =BS!D22-BS!C22 -> 30445613 | E24: =BS!E22-BS!D22 -> 41927771 | F24: =BS!F22-BS!E22 -> 1.5403762e+08 | G24: =BS!G22-BS!F22 -> 4.1474826e+08
B25: Trade payables | C25: =BS!C20-[2]BS!$D$23 -> -69383838 | D25: =BS!D20-BS!C20 -> -1.3760475e+08 | E25: =BS!E20-BS!D20 -> 54188317 | F25: =BS!F20-BS!E20 -> 1.0346269e+08 | G25: =BS!G20-BS!F20 -> 1.416741e+08
B26: Trade receivables | C26: =[2]BS!$D$42-BS!C39 -> 80420511 | D26: =BS!C39-BS!D39 -> 1.9295766e+08 | E26: =BS!D39-BS!E39 -> -94961396 | F26: =BS!E39-BS!F39 -> -2.0990874e+08 | G26: =BS!F39-BS!G39 -> -3.9215109e+08
B27: Cash Generated From Operations Before Tax | C27: =C14+C16+C17+C18+C19+C20+C21+C22+C23+C24+C25+C26 -> 1.1880666e+08 | D27: =D14+D16+D17+D18+D19+D20+D21+D22+D23+D24+D25+D26 -> 3.9438052e+08 | E27: =E14+E16+E17+E18+E19+E20+E21+E22+E23+E24+E25+E26 -> 2.7256614e+08 | F27: =F14+F16+F17+F18+F19+F20+F21+F22+F23+F24+F25+F26 -> 9.5047814e+08 | G27: =G14+G16+G17+G18+G19+G20+G21+G22+G23+G24+G25+G26 -> 2.866124e+09
B28: Income Tax Paid | C28: =IS!C32 -> 53158258 | D28: =IS!D32 -> 83603871 | E28: =IS!E32 -> 1.2553164e+08 | F28: =IS!F32 -> 2.7956927e+08 | G28: =IS!G32 -> 6.9431753e+08
B29: Cash Flow Before Prior Period Items | C29: =C27-C28 -> 65648398 | D29: =D27-D28 -> 3.1077665e+08 | E29: =E27-E28 -> 1.470345e+08 | F29: =F27-F28 -> 6.7090888e+08 | G29: =G27-G28 -> 2.1718065e+09
B30: Net Cash Flow From/(Used In) Operating Activities | C30: =C29 -> 65648398 | D30: =D29 -> 3.1077665e+08 | E30: =E29 -> 1.470345e+08 | F30: =F29 -> 6.7090888e+08 | G30: =G29 -> 2.1718065e+09
B32: CASH FLOW FROM INVESTING ACTIVITIES
B33: Sale Of Asset
B34: Purchase Of Fixed Assets | C34: =BS!C29+BS!C28+IS!C15-[2]BS!$E$32 -> 32150213 | D34: =(BS!D28+BS!D29+IS!D15)-(BS!C28+BS!C29) -> 2.3101422e+08 | E34: =(BS!E28+BS!E29+IS!E15)-(BS!D28+BS!D29) -> 1.4009255e+08 | F34: =(BS!F28+BS!F29+IS!F15)-(BS!E28+BS!E29) -> 2.0804307e+08 | G34: =(BS!G28+BS!G29+IS!G15)-(BS!F28+BS!F29) -> 3.0918568e+08
B35: Increase In Advance And Others
B36: Net Cash Flow From/(Used In) Investing Activities | C36: =SUM(C33:C35) -> 32150213 | D36: =SUM(D33:D35) -> 2.3101422e+08 | E36: =SUM(E33:E35) -> 1.4009255e+08 | F36: =SUM(F33:F35) -> 2.0804307e+08 | G36: =SUM(G33:G35) -> 3.0918568e+08
B38: CASH FLOW FROM FINANCING ACTIVITIES
B39: Proceeds From Issue Of Shares | C39: =Notes!C79+BS!D8-BS!C8 -> 54953891 | D39: =(BS!D8-BS!C8)+Notes!D79 -> 161376150 | E39: 0 | F39: 0 | G39: 0
B40: Proceeds From Long Term Borrowings | C40: =BS!C12-[2]BS!$D$15 -> -58544081 | D40: =BS!D12-BS!C12 -> 24624975 | E40: =BS!E12-BS!D12 -> -21952150 | F40: =BS!F12-BS!E12 -> -10868725 | G40: =BS!G12-BS!F12 -> -10999230
B41: Dividend proposal /distribution
B42: Payment Of Interest And Finance Charges | C42: =-C13 -> -49550008 | D42: =-D13 -> -39745847 | E42: =-E13 -> -38683493 | F42: =-F13 -> -36596332 | G42: =-G13 -> -35347439
B43: Net Cash Flow From/(Used In) Financing Activities | C43: =SUM(C39:C42) -> -53140198 | D43: =SUM(D39:D42) -> 1.4625528e+08 | E43: =SUM(E39:E42) -> -60635643 | F43: =SUM(F39:F42) -> -47465057 | G43: =SUM(G39:G42) -> -46346669
B45: Net Increase / (Decrease) In Cash And Cash Equivalents | C45: =C30-C36+C43 -> -19642013 | D45: =D30-D36+D43 -> 2.260177e+08 | E45: =E30-E36+E43 -> -53693692 | F45: =F30-F36+F43 -> 4.1540074e+08 | G45: =G30-G36+G43 -> 1.8162742e+09
B46: Cash And Cash Equivalents At The Beginning Of The Year | C46: =[2]BS!$D$43 -> 25778362 | D46: =C47 -> 6136348.2 | E46: =D47 -> 2.3215405e+08 | F46: =E47 -> 1.7846036e+08 | G46: =F47 -> 5.938611e+08
B47: Cash And Cash Equivalents At The End Of The Year | C47: =SUM(C45:C46) -> 6136348.2 | D47: =SUM(D45:D46) -> 2.3215405e+08 | E47: =SUM(E45:E46) -> 1.7846036e+08 | F47: =SUM(F45:F46) -> 5.938611e+08 | G47: =SUM(G45:G46) -> 2.4101353e+09

Sheet Notes
B2: POPEES BABY CARE PRODUCTS LIMITED
B3: NOTES TO ACCOUNTS
B5: REVENUE FROM OPERATIONS
B6: Particulars | C6: 46112 | D6: 46477 | E6: 46843 | F6: 47208 | G6: 47573 | H6: 47938
B7: Sale of Products | C7: 1.6195066e+09 | D7: 2.3612595e+09 | E7: 3.3107669e+09 | F7: 5.4096996e+09 | G7: 9.3310172e+09 | H7: 1.1663771e+10
B8: Sales Others | C8: 524824.2 | D8: 512230.96 | E8: 618756.76 | F8: 773445.95 | G8: 966807.44 | H8: 1208509.3
B9: Total | C9: =SUM(C7:C8) -> 1.6200314e+09 | D9: =SUM(D7:D8) -> 2.3617717e+09 | E9: =SUM(E7:E8) -> 3.3113857e+09 | F9: =SUM(F7:F8) -> 5.4104731e+09 | G9: =SUM(G7:G8) -> 9.331984e+09 | H9: =SUM(H7:H8) -> 1.166498e+10
B11: OTHER INCOME
B12: Particulars | C12: 46112 | D12: 46477 | E12: 46843 | F12: 47208 | G12: 47573 | H12: 47938
B13: Discount Received | C13: 1718 | D13: 2500 | E13: 3000 | F13: 3500 | G13: 4000 | H13: 4500
B14: Franchise Fee Received | C14: 1000000 | D14: 5000000 | E14: 6000000 | F14: 8000000 | G14: 9000000 | H14: 10000000
B15: Freight Charges Collected | C15: 117510.39 | D15: 150000 | E15: 175000 | F15: 200000 | G15: 225000 | H15: 250000
B16: Interest on Deposits | C16: 915938.64 | D16: =C16*107% -> 980054.34 | E16: =D16*107% -> 1048658.1 | F16: =E16*107% -> 1122064.2 | G16: =F16*107% -> 1200608.7 | H16: =G16*107% -> 1284651.3
B17: Other Miscellaneous Income | C17: 1246578 | D17: 1500000 | E17: 1500000 | F17: 1500000 | G17: 1500000 | H17: 1500000
B18: Customs Duty Drawback/Incentive | C18: 126745 | D18: 175000 | E18: 250000 | F18: 300000 | G18: 350000 | H18: 400000
B19: Software/IT Support Service Income from Sister Concern | C19: 603250 | D19: 180000 | E19: 180000 | F19: 180000 | G19: 180000 | H19: 180000
B20: Total | C20: =SUM(C13:C19) -> 4011740 | D20: =SUM(D13:D19) -> 7987554.3 | E20: =SUM(E13:E19) -> 9156658.1 | F20: =SUM(F13:F19) -> 11305564 | G20: =SUM(G13:G19) -> 12459609 | H20: =SUM(H13:H19) -> 13619151
B22: COST OF GOODS SOLD
B23: Particulars | C23: 46112 | D23: 46477 | E23: 46843 | F23: 47208 | G23: 47573 | H23: 47938
B24: Cost of Material Consumed | C24: 9.2332175e+08 | D24: 8.4569884e+08 | E24: =E7*56.27%-251317138.77-224069415.76 -> 1.387582e+09 | F24: =F7*56.27%-346376107.37-275453004.77 -> 2.4222089e+09 | G24: =G7*56.27%-1062368954-349244581.83 -> 3.8389498e+09 | H24: =H7*56.27%-1170483963-414462285.93 -> 4.978258e+09
B25: Outsourcing Charges | C25: 13678246 | D25: 4900000 | E25: 5000000 | F25: 7500000 | G25: 10000000 | H25: 15000000
B26: Employee Benefits | C26: 1.005789e+08 | D26: 1.4031233e+08 | E26: =D26*115% -> 1.6135918e+08 | F26: =E26*115% -> 1.8556305e+08 | G26: =F26*115% -> 2.1339751e+08 | H26: =G26*115% -> 2.4540714e+08
B27: Transportation and Delivery Charges | C27: 15736427 | D27: 10265976 | E27: =E7*0.01 -> 33107669 | F27: =F7*0.01 -> 54096996 | G27: =G7*0.01 -> 93310172 | H27: =H7*0.01 -> 1.1663771e+08
B28: Other Factory Related Cost | C28: 25663864 | D28: 21393540 | E28: =D28*115% -> 24602571 | F28: =E28*115% -> 28292957 | G28: =F28*115% -> 32536900 | H28: =G28*115% -> 37417435
B29: COST OF GOODS SOLD | C29: =SUM(C24:C28) -> 1.0789792e+09 | D29: =SUM(D24:D28) -> 1.0225707e+09 | E29: =SUM(E24:E28) -> 1.6116514e+09 | F29: =SUM(F24:F28) -> 2.6976619e+09 | G29: =SUM(G24:G28) -> 4.1881944e+09 | H29: =SUM(H24:H28) -> 5.3927203e+09
B32: EMPLOYEE BENEFIT EXPENSES
B33: Particulars | C33: 46112 | D33: 46477 | E33: 46843 | F33: 47208 | G33: 47573 | H33: 47938
B34: Contribution to provident and other fund | C34: 683806 | D34: =1500000-123624 -> 1376376 | E34: =D34*105% -> 1445194.8 | F34: =E34*105% -> 1517454.5 | G34: =F34*105% -> 1593327.3 | H34: =G34*105% -> 1672993.6
B35: Gratuity | C35: 559818.87 | D35: 753264 | E35: =D35*105% -> 790927.2 | F35: =E35*105% -> 830473.56 | G35: =F35*105% -> 871997.24 | H35: =G35*105% -> 915597.1
B36: Salaries and wages | C36: =81236967.23-1243625 -> 79993342 | D36: 1.769217e+08 | E36: 1.929713e+08 | F36: 2.0261987e+08 | G36: 2.1275086e+08 | H36: 2.2338841e+08
B37: Staff welfare expenses | C37: 15015175 | D37: 16878360 | E37: =D37*105% -> 17722278 | F37: =E37*105% -> 18608392 | G37: =F37*105% -> 19538811 | H37: =G37*105% -> 20515752
B38: Total | C38: =SUM(C34:C37) -> 96252142 | D38: =SUM(D34:D37) -> 1.959297e+08 | E38: =SUM(E34:E37) -> 2.129297e+08 | F38: =SUM(F34:F37) -> 2.2357619e+08 | G38: =SUM(G34:G37) -> 2.34755e+08 | H38: =SUM(H34:H37) -> 2.4649275e+08
B41: OTHER EXPENSES
B42: Particulars | C42: 46112 | D42: 46477 | E42: 46843 | F42: 47208 | G42: 47573 | H42: 47938
B43: Frieght and forwarding | C43: 4941418.8 | D43: 6176773.5 | E43: 6485612.1 | F43: 6809892.7 | G43: 7150387.4 | H43: 7507906.7
B44: Loading and unloading charges | C44: 361469 | D44: 766882.14 | E44: 805226.25 | F44: 845487.56 | G44: 887761.94 | H44: 932150.04
B45: Administration Expense | C45: 203903.6 | D45: 308546.93 | E45: 323974.27 | F45: 340172.99 | G45: 357181.64 | H45: 375040.72
B46: Advertisement Expense | C46: 1314673 | D46: 58758066 | E46: 61695969 | F46: 64780768 | G46: 68019806 | H46: 71420796
B47: Audit Fee | C47: 130560 | D47: 150000 | E47: 157500 | F47: 165375 | G47: 173643.75 | H47: 182325.94
B48: Commission & Brokerage | C48: =31704592.75+15358890.76 -> 47063484 | D48: 2.4473591e+08 | E48: 3.4299546e+08 | F48: 5.6044488e+08 | G48: 9.6669338e+08 | H48: 1.2083667e+09
B49: Consulting Fee | C49: 350641.63 | D49: 350000 | E49: 367500 | F49: 385875 | G49: 405168.75 | H49: 425427.19
B50: Discount Allowed | C50: 9020439.8 | D50: 76668512 | E50: 1.0759993e+08 | F50: 1.7581524e+08 | G50: 3.0325806e+08 | H50: 3.7907257e+08
B51: Documentation &Processing Charges | C51: 693564.26 | D51: 750000 | E51: 787500 | F51: 826875 | G51: 868218.75 | H51: 911629.69
B52: Insurance | C52: 659246.97 | D52: 1126817 | E52: 1183157.9 | F52: 1242315.7 | G52: 1304431.5 | H52: 1369653.1
B53: Incentives to Staff | D53: 29022567 | E53: 30473695 | F53: 31997380 | G53: 33597249 | H53: 35277112
B54: Legal and professional charges | C54: 5413046 | D54: 7500000 | E54: 7875000 | F54: 8268750 | G54: 8682187.5 | H54: 9116296.9
B55: Miscellaneous Expense | C55: =366601+211953.25 -> 578554.25 | D55: 736615.27 | E55: 773446.03 | F55: 812118.34 | G55: 852724.25 | H55: 895360.47
B56: Office Expense | C56: 181787.66 | D56: 272681.49 | E56: 286315.56 | F56: 300631.34 | G56: 315662.91 | H56: 331446.06
B57: Power and Fuel | C57: 4127343.5 | D57: 29471820 | E57: 30945411 | F57: 32492682 | G57: 34117316 | H57: 35823181
B58: Printing and Stationery | C58: 2776352.2 | D58: 3331622.7 | E58: 3498203.8 | F58: 3673114 | G58: 3856769.7 | H58: 4049608.2
B59: Rates and taxes | C59: =16700+830194.8 -> 846894.8 | D59: 1431026 | E59: 1502577.3 | F59: 1577706.2 | G59: 1656591.5 | H59: 1739421
B60: Registration and Renewal charges | C60: 1300603.6 | D60: 1500000 | E60: 1575000 | F60: 1653750 | G60: 1736437.5 | H60: 1823259.4
B61: Rent | C61: =15156984.94+112500+479896.17+11647761.6 -> 27397143 | D61: 181005220 | E61: 190055481 | F61: 1.9955826e+08 | G61: 2.0953617e+08 | H61: 2.2001298e+08
B62: Repairs and Maintenance | C62: 6265830.1 | D62: 15000000 | E62: 15750000 | F62: 16537500 | G62: 17364375 | H62: 18232594
B63: Rounding Off | C63: 10712.37 | D63: 15000 | E63: 15750 | F63: 16537.5 | G63: 17364.375 | H63: 18232.594
B64: Sample Purchased | C64: =270782.27+27730 -> 298512.27 | D64: 447768.41 | E64: 470156.83 | F64: 493664.67 | G64: 518347.9 | H64: 544265.29
B65: Security Service Charges | C65: 201850 | D65: 468000 | E65: 491400 | F65: 515970 | G65: 541768.5 | H65: 568856.93
B66: Selling expense and sales promotion | C66: =8821754.12+192112.22+284845 -> 9298711.3 | D66: 10793506 | E66: 11333181 | F66: 11899840 | G66: 12494832 | H66: 13119574
B67: Software & IT Expense | C67: 6206818.6 | D67: 15816000 | E67: 16606800 | F67: 17437140 | G67: 18308997 | H67: 19224447
B68: Subscriptions & Membership Charges | C68: 1029041.1 | D68: 1543561.6 | E68: 1620739.7 | F68: 1701776.7 | G68: 1786865.5 | H68: 1876208.8
B69: Telephone, telegram and postage | C69: 1968250.5 | D69: 2386110 | E69: 2505415.5 | F69: 2630686.3 | G69: 2762220.6 | H69: 2900331.7
B70: Transportation Charges | C70: 477708.74 | D70: 11119828 | E70: 11675819 | F70: 12259610 | G70: 12872590 | H70: 13516220
B71: Travelling Expense | C71: 15867988 | D71: 17311147 | E71: 18176705 | F71: 19085540 | G71: 20039817 | H71: 21041808
B72: Water Charges | C72: 236650 | D72: 306816.72 | E72: 322157.56 | F72: 338265.44 | G72: 355178.71 | H72: 372937.65
B73: Total | C73: =SUM(C43:C72) -> 1.492232e+08 | D73: =SUM(D43:D72) -> 7.192708e+08 | E73: =SUM(E43:E72) -> 8.6835508e+08 | F73: =SUM(F43:F72) -> 1.1749078e+09 | G73: =SUM(G43:G72) -> 1.7305315e+09 | H73: =SUM(H43:H72) -> 2.0710484e+09
B75: RESERVES AND SURPLUS
B76: Particulars | C76: 46112 | D76: 46477 | E76: 46843 | F76: 47208 | G76: 47573 | H76: 47938
B77: (A) Securities premium account
B78: Opening balance | C78: 505852510 | D78: =C81 -> 550047991 | E78: =D81 -> 700665731 | F78: =E81 -> 700665731 | G78: =F81 -> 700665731 | H78: =G81 -> 700665731
B79: Add: Additions during the year | C79: 44195481 | D79: 150617740 | E79: 0 | F79: 0 | G79: 0 | H79: 0
B80: Less: Appropriations during the year
B81: Closing balance | C81: =C78+C79-C80 -> 550047991 | D81: =D78+D79-D80 -> 700665731 | E81: =E78+E79-E80 -> 700665731 | F81: =F78+F79-F80 -> 700665731 | G81: =G78+G79-G80 -> 700665731 | H81: =H78+H79-H80 -> 700665731
B83: (B) Surplus / (Deficit) in Statement of Profit and Loss
B84: Opening balance | C84: 92669380 | D84: =C89 -> 2.7577005e+08 | E84: =D89 -> 5.6373893e+08 | F84: =E89 -> 9.961257e+08 | G84: =F89 -> 1.9590865e+09 | H84: =G89 -> 4.3506246e+09
B85: Profit / (Loss) for the year | C85: =IS!C41 -> 1.8310067e+08 | D85: =IS!D41 -> 2.8796889e+08 | E85: =IS!E41 -> 4.3238677e+08 | F85: =IS!F41 -> 9.629608e+08 | G85: =IS!G41 -> 2.3915381e+09 | H85: =IS!H41 -> 2.9680531e+09
B86: Less: Dividend Declared and Paid
B87: Less:- Bouns share issued | C87: 0 | E87: 0
B89: Closing balance | C89: =C84+C85-C86-C87 -> 2.7577005e+08 | D89: =D84+D85-D86-D87 -> 5.6373893e+08 | E89: =E84+E85-E86-E87 -> 9.961257e+08 | F89: =F84+F85-F86-F87 -> 1.9590865e+09 | G89: =G84+G85-G86-G87 -> 4.3506246e+09 | H89: =H84+H85-H86-H87 -> 7.3186778e+09
B91: Total | C91: =C81+C89 -> 8.2581804e+08 | D91: =D81+D89 -> 1.2644047e+09 | E91: =E81+E89 -> 1.6967914e+09 | F91: =F81+F89 -> 2.6597522e+09 | G91: =G81+G89 -> 5.0512904e+09 | H91: =H81+H89 -> 8.0193435e+09
B93: LONG TERM BORROWINGS
B94: Particulars | C94: 46112 | D94: 46477 | E94: 46843 | F94: 47208 | G94: 47573 | H94: 47938
B95: a) Term Loans
B96: i) From banks
B97: Secured | C97: =BS!C12 -> 32690547 | D97: =BS!D12 -> 57315522 | E97: =BS!E12 -> 35363372 | F97: =BS!F12 -> 24494647 | G97: =BS!G12 -> 13495417 | H97: =BS!H12 -> 1101210
B98: Less: Payable within next 12 months treated as Current Liabilities
B99: Vehicle Loans
B100: ii)From other parties
B101: Secured
B102: Unsecured
B103: b) Loan from Director & Relatives
B104: Loan From Directors
B105: Loan From Others
B106: Loan From Share Holders
B107: TOTAL | C107: =SUM(C99:C106,C97)-C98 -> 32690547 | D107: =SUM(D99:D106,D97)-D98 -> 57315522 | E107: =SUM(E99:E106,E97)-E98 -> 35363372 | F107: =SUM(F99:F106,F97)-F98 -> 24494647 | G107: =SUM(G99:G106,G97)-G98 -> 13495417 | H107: =SUM(H99:H106,H97)-H98 -> 1101210
B109: Note 5 OTHER LONG-TERM LIABILITIES
B110: Particulars | C110: 46112 | D110: 46477 | E110: 46843 | F110: 47208 | G110: 47573 | H110: 47938
B111: Deposit from Distributors/Customers | C111: 1.1190467e+08 | D111: =C111+50000000 -> 1.6190467e+08 | E111: =D111+50000000 -> 2.1190467e+08 | F111: =E111+50000000 -> 2.6190467e+08 | G111: =F111+50000000 -> 3.1190467e+08 | H111: =G111+50000000 -> 3.6190467e+08
B113: Total | C113: =SUM(C111:C111) -> 1.1190467e+08 | D113: =SUM(D111:D111) -> 1.6190467e+08 | E113: =SUM(E111:E111) -> 2.1190467e+08 | F113: =SUM(F111:F111) -> 2.6190467e+08 | G113: =SUM(G111:G111) -> 3.1190467e+08 | H113: =SUM(H111:H111) -> 3.6190467e+08
B115: LONG-TERM PROVISIONS
B116: Particulars | C116: 46112 | D116: 46477 | E116: 46843 | F116: 47208 | G116: 47573 | H116: 47938
...

Sheet EMI SCHEDULE KOTAK
B2: Kotak Bank Term Laon EMI Schedule
B3: Disbursment Expected | C3: 01.06.2026
B4: Rate of Interest | C4: 0.12
B5: Amount Disbursed | C5: 50000000
B7: Month & Year | C7: Principal | D7: Interest | E7: EMI | F7: Outstanding | G7: Interest Payment
B8: May-2026 | C8: 612222 | D8: 500000 | E8: 1112222 | F8: 49387778
B9: Jun-2026 | C9: 618345 | D9: 493878 | E9: 1112222 | F9: 48769433
B10: Jul-2026 | C10: 624528 | D10: 487694 | E10: 1112222 | F10: 48144905
B11: Aug-2026 | C11: 630773 | D11: 481449 | E11: 1112222 | F11: 47514132
B12: Sep-2026 | C12: 637081 | D12: 475141 | E12: 1112222 | F12: 46877051
B13: Oct-2026 | C13: 643452 | D13: 468771 | E13: 1112222 | F13: 46233599
B14: Nov-2026 | C14: 649886 | D14: 462336 | E14: 1112222 | F14: 45583712
B15: Dec-2026 | C15: 656385 | D15: 455837 | E15: 1112222 | F15: 44927327
B16: Jan-2027 | C16: 662949 | D16: 449273 | E16: 1112222 | F16: 44264378
B17: Feb-2027 | C17: 669579 | D17: 442644 | E17: 1112222 | F17: 43594799
B18: Mar-2027 | C18: 676274 | D18: 435948 | E18: 1112222 | F18: 42918525 | G18: =SUM(D8:D18) -> 5152971
B19: Apr-2027 | C19: 683037 | D19: 429185 | E19: 1112222 | F19: 42235488
B20: May-2027 | C20: 689868 | D20: 422355 | E20: 1112222 | F20: 41545620
B21: Jun-2027 | C21: 696766 | D21: 415456 | E21: 1112222 | F21: 40848854
B22: Jul-2027 | C22: 703734 | D22: 408489 | E22: 1112222 | F22: 40145120
B23: Aug-2027 | C23: 710771 | D23: 401451 | E23: 1112222 | F23: 39434349
B24: Sep-2027 | C24: 717879 | D24: 394343 | E24: 1112222 | F24: 38716470
B25: Oct-2027 | C25: 725058 | D25: 387165 | E25: 1112222 | F25: 37991412
B26: Nov-2027 | C26: 732308 | D26: 379914 | E26: 1112222 | F26: 37259104
B27: Dec-2027 | C27: 739631 | D27: 372591 | E27: 1112222 | F27: 36519473
B28: Jan-2028 | C28: 747028 | D28: 365195 | E28: 1112222 | F28: 35772445
B29: Feb-2028 | C29: 754498 | D29: 357724 | E29: 1112222 | F29: 35017947
B30: Mar-2028 | C30: 762043 | D30: 350179 | E30: 1112222 | F30: 34255904 | G30: =SUM(D19:D30) -> 4684047
B31: Apr-2028 | C31: 769663 | D31: 342559 | E31: 1112222 | F31: 33486241
B32: May-2028 | C32: 777360 | D32: 334862 | E32: 1112222 | F32: 32708881
B33: Jun-2028 | C33: 785134 | D33: 327089 | E33: 1112222 | F33: 31923747
B34: Jul-2028 | C34: 792985 | D34: 319237 | E34: 1112222 | F34: 31130763
B35: Aug-2028 | C35: 800915 | D35: 311308 | E35: 1112222 | F35: 30329848
B36: Sep-2028 | C36: 808924 | D36: 303298 | E36: 1112222 | F36: 29520924
B37: Oct-2028 | C37: 817013 | D37: 295209 | E37: 1112222 | F37: 28703911
B38: Nov-2028 | C38: 825183 | D38: 287039 | E38: 1112222 | F38: 27878727
B39: Dec-2028 | C39: 833435 | D39: 278787 | E39: 1112222 | F39: 27045292
B40: Jan-2029 | C40: 841769 | D40: 270453 | E40: 1112222 | F40: 26203523
B41: Feb-2029 | C41: 850187 | D41: 262035 | E41: 1112222 | F41: 25353336
B42: Mar-2029 | C42: 858689 | D42: 253533 | E42: 1112222 | F42: 24494647 | G42: =SUM(D31:D42) -> 3585409
B43: Apr-2029 | C43: 867276 | D43: 244946 | E43: 1112222 | F43: 23627371
B44: May-2029 | C44: 875949 | D44: 236274 | E44: 1112222 | F44: 22751422
B45: Jun-2029 | C45: 884708 | D45: 227514 | E45: 1112222 | F45: 21866714
B46: Jul-2029 | C46: 893555 | D46: 218667 | E46: 1112222 | F46: 20973159
B47: Aug-2029 | C47: 902491 | D47: 209732 | E47: 1112222 | F47: 20070668
B48: Sep-2029 | C48: 911516 | D48: 200707 | E48: 1112222 | F48: 19159152
B49: Oct-2029 | C49: 920631 | D49: 191592 | E49: 1112222 | F49: 18238521
B50: Nov-2029 | C50: 929837 | D50: 182385 | E50: 1112222 | F50: 17308684
B51: Dec-2029 | C51: 939136 | D51: 173087 | E51: 1112222 | F51: 16369549
B52: Jan-2030 | C52: 948527 | D52: 163695 | E52: 1112222 | F52: 15421022
B53: Feb-2030 | C53: 958012 | D53: 154210 | E53: 1112222 | F53: 14463010
B54: Mar-2030 | C54: 967592 | D54: 144630 | E54: 1112222 | F54: 13495417 | G54: =SUM(D43:D54) -> 2347439
B55: Apr-2030 | C55: 977268 | D55: 134954 | E55: 1112222 | F55: 12518149
B56: May-2030 | C56: 987041 | D56: 125181 | E56: 1112222 | F56: 11531108
B57: Jun-2030 | C57: 996911 | D57: 115311 | E57: 1112222 | F57: 10534197
B58: Jul-2030 | C58: 1006880 | D58: 105342 | E58: 1112222 | F58: 9527316
B59: Aug-2030 | C59: 1016949 | D59: 95273 | E59: 1112222 | F59: 8510367
B60: Sep-2030 | C60: 1027119 | D60: 85104 | E60: 1112222 | F60: 7483249
B61: Oct-2030 | C61: 1037390 | D61: 74832 | E61: 1112222 | F61: 6445859
B62: Nov-2030 | C62: 1047764 | D62: 64459 | E62: 1112222 | F62: 5398095
B63: Dec-2030 | C63: 1058241 | D63: 53981 | E63: 1112222 | F63: 4339853
B64: Jan-2031 | C64: 1068824 | D64: 43399 | E64: 1112222 | F64: 3271030
B65: Feb-2031 | C65: 1079512 | D65: 32710 | E65: 1112222 | F65: 2191517
B66: Mar-2031 | C66: 1090307 | D66: 21915 | E66: 1112222 | F66: 1101210 | G66: =SUM(D55:D66) -> 952461
B67: Apr-2031 | C67: 1101210 | D67: 11012 | E67: 1112222 | F67: 0
B69: Cash Credit | C69: 2027 | D69: 2028 | E69: 2029 | F69: 2030 | G69: 2031
B70: Amount Sanctioned | C70: 325000000 | D70: 275000000 | E70: 275000000 | F70: 275000000 | G70: 275000000
B71: Interest @ 12% | C71: =C70*12%/12*10 -> 32500000 | D71: =D70*12% -> 33000000 | E71: =E70*12% -> 33000000 | F71: =F70*12% -> 33000000 | G71: =G70*12% -> 33000000
B73: SUMMARY | C73: 2027 | D73: 2028 | E73: 2029 | F73: 2030 | G73: 2031
B74: Finance Charges | C74: =C71+G18+GECL!H13+GECL!H40+GECL!H67+GECL!H94+GECL!H118 -> 39745847 | D74: =D71+G30+GECL!H25+GECL!H52+GECL!H79+GECL!H106 -> 38683493 | E74: =E71+G42+GECL!H26+GECL!H53+GECL!H80+GECL!H107 -> 36596332 | F74: =F71+G54 -> 35347439 | G74: =G66+G71 -> 33952461
B75: Loan Outstanding | C75: =F18+GECL!G13+GECL!G40+GECL!G67+GECL!G94 -> 57315522 | D75: =F30+GECL!G25+GECL!G52+GECL!G79+GECL!G106 -> 35363372 | E75: =F42 -> 24494647 | F75: =F54 -> 13495417 | G75: =F66 -> 1101210

Sheet GECL
B1: UNION BANK OF INDIA
B2: WCDL | C2: Days | D2: Principal | E2: Interest | F2: EMI | G2: BALANCE
B3: 46174 | G3: 13416667
B4: 46203 | C4: =B4-B3 -> 29 | D4: 583333 | E4: =G3*12%*C4/365 -> 127917.81 | F4: =D4+E4 -> 711250.81 | G4: =G3-D4 -> 12833334
B5: 46234 | C5: =B5-B4 -> 31 | D5: 583333 | E5: =G4*12%*C5/365 -> 130794.53 | F5: =D5+E5 -> 714127.53 | G5: =G4-D5 -> 12250001
B6: 46265 | C6: =B6-B5 -> 31 | D6: 583333 | E6: =G5*12%*C6/365 -> 124849.32 | F6: =D6+E6 -> 708182.32 | G6: =G5-D6 -> 11666668
B7: 46295 | C7: =B7-B6 -> 30 | D7: 583333 | E7: =G6*12%*C7/365 -> 115068.5 | F7: =D7+E7 -> 698401.5 | G7: =G6-D7 -> 11083335
B8: 46326 | C8: =B8-B7 -> 31 | D8: 583333 | E8: =G7*12%*C8/365 -> 112958.92 | F8: =D8+E8 -> 696291.92 | G8: =G7-D8 -> 10500002
B9: 46356 | C9: =B9-B8 -> 30 | D9: 583333 | E9: =G8*12%*C9/365 -> 103561.66 | F9: =D9+E9 -> 686894.66 | G9: =G8-D9 -> 9916668.8
B10: 46387 | C10: =B10-B9 -> 31 | D10: 583333 | E10: =G9*12%*C10/365 -> 101068.51 | F10: =D10+E10 -> 684401.51 | G10: =G9-D10 -> 9333335.8
B11: 46418 | C11: =B11-B10 -> 31 | D11: 583333 | E11: =G10*12%*C11/365 -> 95123.313 | F11: =D11+E11 -> 678456.31 | G11: =G10-D11 -> 8750002.8
B12: 46446 | C12: =B12-B11 -> 28 | D12: 583333 | E12: =G11*12%*C12/365 -> 80547.971 | F12: =D12+E12 -> 663880.97 | G12: =G11-D12 -> 8166669.8
B13: 46477 | C13: =B13-B12 -> 31 | D13: 583333 | E13: =G12*12%*C13/365 -> 83232.909 | F13: =D13+E13 -> 666565.91 | G13: =G12-D13 -> 7583336.8 | H13: =SUM(E4:E13) -> 1075123.4
B14: 46507 | C14: =B14-B13 -> 30 | D14: 583333 | E14: =G13*12%*C14/365 -> 74794.555 | F14: =D14+E14 -> 658127.55 | G14: =G13-D14 -> 7000003.8
B15: 46538 | C15: =B15-B14 -> 31 | D15: 583333 | E15: =G14*12%*C15/365 -> 71342.504 | F15: =D15+E15 -> 654675.5 | G15: =G14-D15 -> 6416670.8
B16: 46568 | C16: =B16-B15 -> 30 | D16: 583333 | E16: =G15*12%*C16/365 -> 63287.712 | F16: =D16+E16 -> 646620.71 | G16: =G15-D16 -> 5833337.8
B17: 46599 | C17: =B17-B16 -> 31 | D17: 583333 | E17: =G16*12%*C17/365 -> 59452.1 | F17: =D17+E17 -> 642785.1 | G17: =G16-D17 -> 5250004.8
B18: 46630 | C18: =B18-B17 -> 31 | D18: 583333 | E18: =G17*12%*C18/365 -> 53506.898 | F18: =D18+E18 -> 636839.9 | G18: =G17-D18 -> 4666671.8
B19: 46660 | C19: =B19-B18 -> 30 | D19: 583333 | E19: =G18*12%*C19/365 -> 46027.448 | F19: =D19+E19 -> 629360.45 | G19: =G18-D19 -> 4083338.8
B20: 46691 | C20: =B20-B19 -> 31 | D20: 583333 | E20: =G19*12%*C20/365 -> 41616.494 | F20: =D20+E20 -> 624949.49 | G20: =G19-D20 -> 3500005.8
B21: 46721 | C21: =B21-B20 -> 30 | D21: 583333 | E21: =G20*12%*C21/365 -> 34520.605 | F21: =D21+E21 -> 617853.61 | G21: =G20-D21 -> 2916672.8
B22: 46752 | C22: =B22-B21 -> 31 | D22: 583333 | E22: =G21*12%*C22/365 -> 29726.09 | F22: =D22+E22 -> 613059.09 | G22: =G21-D22 -> 2333339.8
B23: 46783 | C23: =B23-B22 -> 31 | D23: 583333 | E23: =G22*12%*C23/365 -> 23780.888 | F23: =D23+E23 -> 607113.89 | G23: =G22-D23 -> 1750006.8
B24: 46811 | C24: =B24-B23 -> 28 | D24: 583333 | E24: =G23*12%*C24/365 -> 16109.652 | F24: =D24+E24 -> 599442.65 | G24: =G23-D24 -> 1166673.8
B25: 46843 | C25: =B25-B24 -> 32 | D25: 583333 | E25: =G24*12%*C25/365 -> 12274.048 | F25: =D25+E25 -> 595607.05 | G25: =G24-D25 -> 583340.79 | H25: =SUM(E14:E25) -> 526438.99
B26: 46873 | C26: =B26-B25 -> 30 | D26: =583333+7.79 -> 583340.79 | E26: =G25*12%*C26/365 -> 5753.4982 | F26: =D26+E26 -> 589094.29 | G26: =G25-D26 -> -9.3132257e-10 | H26: =SUM(E26) -> 5753.4982
B28: UBI TL 007
B29: TERM LOAN | C29: Days | D29: Principal | E29: Interest | F29: EMI | G29: BALANCE
B30: 46174 | G30: 2412956.2
B31: 46203 | C31: =B31-B30 -> 29 | D31: =105000-88.86 -> 104911.14 | E31: =G30*12%*C31/365 -> 23005.72 | F31: =D31+E31 -> 127916.86 | G31: =G30-D31 -> 2308045.1
B32: 46234 | C32: =B32-B31 -> 31 | D32: =105000-88.86 -> 104911.14 | E32: =G31*12%*C32/365 -> 23523.09 | F32: =D32+E32 -> 128434.23 | G32: =G31-D32 -> 2203134
B33: 46265 | C33: =B33-B32 -> 31 | D33: =105000-88.86 -> 104911.14 | E33: =G32*12%*C33/365 -> 22453.858 | F33: =D33+E33 -> 127365 | G33: =G32-D33 -> 2098222.8
B34: 46295 | C34: =B34-B33 -> 30 | D34: =105000-88.86 -> 104911.14 | E34: =G33*12%*C34/365 -> 20694.8 | F34: =D34+E34 -> 125605.94 | G34: =G33-D34 -> 1993311.7
B35: 46326 | C35: =B35-B34 -> 31 | D35: =105000-88.86 -> 104911.14 | E35: =G34*12%*C35/365 -> 20315.396 | F35: =D35+E35 -> 125226.54 | G35: =G34-D35 -> 1888400.5
B36: 46356 | C36: =B36-B35 -> 30 | D36: =105000-88.86 -> 104911.14 | E36: =G35*12%*C36/365 -> 18625.32 | F36: =D36+E36 -> 123536.46 | G36: =G35-D36 -> 1783489.4
B37: 46387 | C37: =B37-B36 -> 31 | D37: =105000-88.86 -> 104911.14 | E37: =G36*12%*C37/365 -> 18176.933 | F37: =D37+E37 -> 123088.07 | G37: =G36-D37 -> 1678578.3
B38: 46418 | C38: =B38-B37 -> 31 | D38: =105000-88.86 -> 104911.14 | E38: =G37*12%*C38/365 -> 17107.702 | F38: =D38+E38 -> 122018.84 | G38: =G37-D38 -> 1573667.1
B39: 46446 | C39: =B39-B38 -> 28 | D39: =105000-88.86 -> 104911.14 | E39: =G38*12%*C39/365 -> 14486.36 | F39: =D39+E39 -> 119397.5 | G39: =G38-D39 -> 1468756
B40: 46477 | C40: =B40-B39 -> 31 | D40: =105000-88.86 -> 104911.14 | E40: =G39*12%*C40/365 -> 14969.239 | F40: =D40+E40 -> 119880.38 | G40: =G39-D40 -> 1363844.8 | H40: =SUM(E31:E40) -> 193358.42
B41: 46507 | C41: =B41-B40 -> 30 | D41: =105000-88.86 -> 104911.14 | E41: =G40*12%*C41/365 -> 13451.62 | F41: =D41+E41 -> 118362.76 | G41: =G40-D41 -> 1258933.7
B42: 46538 | C42: =B42-B41 -> 31 | D42: =105000-88.86 -> 104911.14 | E42: =G41*12%*C42/365 -> 12830.776 | F42: =D42+E42 -> 117741.92 | G42: =G41-D42 -> 1154022.6
B43: 46568 | C43: =B43-B42 -> 30 | D43: =105000-88.86 -> 104911.14 | E43: =G42*12%*C43/365 -> 11382.14 | F43: =D43+E43 -> 116293.28 | G43: =G42-D43 -> 1049111.4
B44: 46599 | C44: =B44-B43 -> 31 | D44: =105000-88.86 -> 104911.14 | E44: =G43*12%*C44/365 -> 10692.314 | F44: =D44+E44 -> 115603.45 | G44: =G43-D44 -> 944200.28
B45: 46630 | C45: =B45-B44 -> 31 | D45: =105000-88.86 -> 104911.14 | E45: =G44*12%*C45/365 -> 9623.0823 | F45: =D45+E45 -> 114534.22 | G45: =G44-D45 -> 839289.14
B46: 46660 | C46: =B46-B45 -> 30 | D46: =105000-88.86 -> 104911.14 | E46: =G45*12%*C46/365 -> 8277.9203 | F46: =D46+E46 -> 113189.06 | G46: =G45-D46 -> 734378
B47: 46691 | C47: =B47-B46 -> 31 | D47: =105000-88.86 -> 104911.14 | E47: =G46*12%*C47/365 -> 7484.6196 | F47: =D47+E47 -> 112395.76 | G47: =G46-D47 -> 629466.86
B48: 46721 | C48: =B48-B47 -> 30 | D48: =105000-88.86 -> 104911.14 | E48: =G47*12%*C48/365 -> 6208.4403 | F48: =D48+E48 -> 111119.58 | G48: =G47-D48 -> 524555.72
B49: 46752 | C49: =B49-B48 -> 31 | D49: =105000-88.86 -> 104911.14 | E49: =G48*12%*C49/365 -> 5346.1569 | F49: =D49+E49 -> 110257.3 | G49: =G48-D49 -> 419644.58
B50: 46783 | C50: =B50-B49 -> 31 | D50: =105000-88.86 -> 104911.14 | E50: =G49*12%*C50/365 -> 4276.9256 | F50: =D50+E50 -> 109188.07 | G50: =G49-D50 -> 314733.44
B51: 46811 | C51: =B51-B50 -> 28 | D51: =105000-88.86 -> 104911.14 | E51: =G50*12%*C51/365 -> 2897.2722 | F51: =D51+E51 -> 107808.41 | G51: =G50-D51 -> 209822.3
B52: 46843 | C52: =B52-B51 -> 32 | D52: =105000-88.86 -> 104911.14 | E52: =G51*12%*C52/365 -> 2207.4456 | F52: =D52+E52 -> 107118.59 | G52: =G51-D52 -> 104911.16 | H52: =SUM(E41:E52) -> 94678.713
B53: 46873 | C53: =B53-B52 -> 30 | D53: =105000-88.84 -> 104911.16 | E53: =G52*12%*C53/365 -> 1034.7402 | F53: =D53+E53 -> 105945.9 | G53: =G52-D53 -> 7.4214768e-10 | H53: =SUM(E53) -> 1034.7402
B55: UBI TL 008
B56: TERM LOAN | C56: Days | D56: Principal | E56: Interest | F56: EMI | G56: BALANCE
B57: 46174 | G57: 2891283.1
B58: 46203 | C58: =B58-B57 -> 29 | D58: =105000-88.86+20796.82 -> 125707.96 | E58: =G57*12%*C58/365 -> 27566.206 | F58: =D58+E58 -> 153274.17 | G58: =G57-D58 -> 2765575.1
B59: 46234 | C59: =B59-B58 -> 31 | D59: =105000-88.86+20796.82 -> 125707.96 | E59: =G58*12%*C59/365 -> 28186.135 | F59: =D59+E59 -> 153894.1 | G59: =G58-D59 -> 2639867.2
B60: 46265 | C60: =B60-B59 -> 31 | D60: =105000-88.86+20796.82 -> 125707.96 | E60: =G59*12%*C60/365 -> 26904.947 | F60: =D60+E60 -> 152612.91 | G60: =G59-D60 -> 2514159.2
B61: 46295 | C61: =B61-B60 -> 30 | D61: =105000-88.86+20796.82 -> 125707.96 | E61: =G60*12%*C61/365 -> 24797.187 | F61: =D61+E61 -> 150505.15 | G61: =G60-D61 -> 2388451.2
B62: 46326 | C62: =B62-B61 -> 31 | D62: =105000-88.86+20796.82 -> 125707.96 | E62: =G61*12%*C62/365 -> 24342.572 | F62: =D62+E62 -> 150050.53 | G62: =G61-D62 -> 2262743.3
B63: 46356 | C63: =B63-B62 -> 30 | D63: =105000-88.86+20796.82 -> 125707.96 | E63: =G62*12%*C63/365 -> 22317.468 | F63: =D63+E63 -> 148025.43 | G63: =G62-D63 -> 2137035.3
B64: 46387 | C64: =B64-B63 -> 31 | D64: =105000-88.86+20796.82 -> 125707.96 | E64: =G63*12%*C64/365 -> 21780.196 | F64: =D64+E64 -> 147488.16 | G64: =G63-D64 -> 2011327.4
B65: 46418 | C65: =B65-B64 -> 31 | D65: =105000-88.86+20796.82 -> 125707.96 | E65: =G64*12%*C65/365 -> 20499.008 | F65: =D65+E65 -> 146206.97 | G65: =G64-D65 -> 1885619.4
B66: 46446 | C66: =B66-B65 -> 28 | D66: =105000-88.86+20796.82 -> 125707.96 | E66: =G65*12%*C66/365 -> 17358.031 | F66: =D66+E66 -> 143065.99 | G66: =G65-D66 -> 1759911.4
B67: 46477 | C67: =B67-B66 -> 31 | D67: =105000-88.86+20796.82 -> 125707.96 | E67: =G66*12%*C67/365 -> 17936.632 | F67: =D67+E67 -> 143644.59 | G67: =G66-D67 -> 1634203.5 | H67: =SUM(E58:E67) -> 231688.38
B68: 46507 | C68: =B68-B67 -> 30 | D68: =105000-88.86+20796.82 -> 125707.96 | E68: =G67*12%*C68/365 -> 16118.171 | F68: =D68+E68 -> 141826.13 | G68: =G67-D68 -> 1508495.5
B69: 46538 | C69: =B69-B68 -> 31 | D69: =105000-88.86+20796.82 -> 125707.96 | E69: =G68*12%*C69/365 -> 15374.256 | F69: =D69+E69 -> 141082.22 | G69: =G68-D69 -> 1382787.6
B70: 46568 | C70: =B70-B69 -> 30 | D70: =105000-88.86+20796.82 -> 125707.96 | E70: =G69*12%*C70/365 -> 13638.453 | F70: =D70+E70 -> 139346.41 | G70: =G69-D70 -> 1257079.6
B71: 46599 | C71: =B71-B70 -> 31 | D71: =105000-88.86+20796.82 -> 125707.96 | E71: =G70*12%*C71/365 -> 12811.88 | F71: =D71+E71 -> 138519.84 | G71: =G70-D71 -> 1131371.6
B72: 46630 | C72: =B72-B71 -> 31 | D72: =105000-88.86+20796.82 -> 125707.96 | E72: =G71*12%*C72/365 -> 11530.692 | F72: =D72+E72 -> 137238.65 | G72: =G71-D72 -> 1005663.7
B73: 46660 | C73: =B73-B72 -> 30 | D73: =105000-88.86+20796.82 -> 125707.96 | E73: =G72*12%*C73/365 -> 9918.8747 | F73: =D73+E73 -> 135626.83 | G73: =G72-D73 -> 879955.72
B74: 46691 | C74: =B74-B73 -> 31 | D74: =105000-88.86+20796.82 -> 125707.96 | E74: =G73*12%*C74/365 -> 8968.3158 | F74: =D74+E74 -> 134676.28 | G74: =G73-D74 -> 754247.76
B75: 46721 | C75: =B75-B74 -> 30 | D75: =105000-88.86+20796.82 -> 125707.96 | E75: =G74*12%*C75/365 -> 7439.156 | F75: =D75+E75 -> 133147.12 | G75: =G74-D75 -> 628539.8
B76: 46752 | C76: =B76-B75 -> 31 | D76: =105000-88.86+20796.82 -> 125707.96 | E76: =G75*12%*C76/365 -> 6405.9399 | F76: =D76+E76 -> 132113.9 | G76: =G75-D76 -> 502831.84
B77: 46783 | C77: =B77-B76 -> 31 | D77: =105000-88.86+20796.82 -> 125707.96 | E77: =G76*12%*C77/365 -> 5124.7519 | F77: =D77+E77 -> 130832.71 | G77: =G76-D77 -> 377123.88
B78: 46811 | C78: =B78-B77 -> 28 | D78: =105000-88.86+20796.82 -> 125707.96 | E78: =G77*12%*C78/365 -> 3471.6061 | F78: =D78+E78 -> 129179.57 | G78: =G77-D78 -> 251415.92
B79: 46843 | C79: =B79-B78 -> 32 | D79: =105000-88.86+20796.82 -> 125707.96 | E79: =G78*12%*C79/365 -> 2645.0332 | F79: =D79+E79 -> 128352.99 | G79: =G78-D79 -> 125707.96 | H79: =SUM(E68:E79) -> 113447.13
B80: 46873 | C80: =B80-B79 -> 30 | D80: =105000-88.86+20796.82 -> 125707.96 | E80: =G79*12%*C80/365 -> 1239.8593 | F80: =D80+E80 -> 126947.82 | G80: =G79-D80 -> 8.4401108e-10 | H80: =SUM(E80) -> 1239.8593
B82: UBI
B83: WCTL | C83: Days | D83: Principal | E83: Interest | F83: EMI | G83: BALANCE
B84: 46174 | G84: 6750698.6
B85: 46203 | C85: =B85-B84 -> 29 | D85: =105000-88.86+20796.82+167800.68 -> 293508.64 | E85: =G84*12%*C85/365 -> 64362.825 | F85: =D85+E85 -> 357871.47 | G85: =G84-D85 -> 6457190
B86: 46234 | C86: =B86-B85 -> 31 | D86: =105000-88.86+20796.82+167800.68 -> 293508.64 | E86: =G85*12%*C86/365 -> 65810.265 | F86: =D86+E86 -> 359318.91 | G86: =G85-D86 -> 6163681.3
B87: 46265 | C87: =B87-B86 -> 31 | D87: =105000-88.86+20796.82+167800.68 -> 293508.64 | E87: =G86*12%*C87/365 -> 62818.889 | F87: =D87+E87 -> 356327.53 | G87: =G86-D87 -> 5870172.7
B88: 46295 | C88: =B88-B87 -> 30 | D88: =105000-88.86+20796.82+167800.68 -> 293508.64 | E88: =G87*12%*C88/365 -> 57897.594 | F88: =D88+E88 -> 351406.23 | G88: =G87-D88 -> 5576664.1
B89: 46326 | C89: =B89-B88 -> 31 | D89: =105000-88.86+20796.82+167800.68 -> 293508.64 | E89: =G88*12%*C89/365 -> 56836.138 | F89: =D89+E89 -> 350344.78 | G89: =G88-D89 -> 5283155.4
B90: 46356 | C90: =B90-B89 -> 30 | D90: =105000-88.86+20796.82+167800.68 -> 293508.64 | E90: =G89*12%*C90/365 -> 52107.834 | F90: =D90+E90 -> 345616.47 | G90: =G89-D90 -> 4989646.8
B91: 46387 | C91: =B91-B90 -> 31 | D91: =105000-88.86+20796.82+167800.68 -> 293508.64 | E91: =G90*12%*C91/365 -> 50853.386 | F91: =D91+E91 -> 344362.03 | G91: =G90-D91 -> 4696138.1
B92: 46418 | C92: =B92-B91 -> 31 | D92: =105000-88.86+20796.82+167800.68 -> 293508.64 | E92: =G91*12%*C92/365 -> 47862.011 | F92: =D92+E92 -> 341370.65 | G92: =G91-D92 -> 4402629.5
B93: 46446 | C93: =B93-B92 -> 28 | D93: =105000-88.86+20796.82+167800.68 -> 293508.64 | E93: =G92*12%*C93/365 -> 40528.315 | F93: =D93+E93 -> 334036.96 | G93: =G92-D93 -> 4109120.9
B94: 46477 | C94: =B94-B93 -> 31 | D94: =105000-88.86+20796.82+167800.68 -> 293508.64 | E94: =G93*12%*C94/365 -> 41879.259 | F94: =D94+E94 -> 335387.9 | G94: =G93-D94 -> 3815612.2 | H94: =SUM(E85:E94) -> 540956.52
B95: 46507 | C95: =B95-B94 -> 30 | D95: =105000-88.86+20796.82+167800.68 -> 293508.64 | E95: =G94*12%*C95/365 -> 37633.436 | F95: =D95+E95 -> 331142.08 | G95: =G94-D95 -> 3522103.6
B96: 46538 | C96: =B96-B95 -> 31 | D96: =105000-88.86+20796.82+167800.68 -> 293508.64 | E96: =G95*12%*C96/365 -> 35896.508 | F96: =D96+E96 -> 329405.15 | G96: =G95-D96 -> 3228594.9
B97: 46568 | C97: =B97-B96 -> 30 | D97: =105000-88.86+20796.82+167800.68 -> 293508.64 | E97: =G96*12%*C97/365 -> 31843.676 | F97: =D97+E97 -> 325352.32 | G97: =G96-D97 -> 2935086.3
B98: 46599 | C98: =B98-B97 -> 31 | D98: =105000-88.86+20796.82+167800.68 -> 293508.64 | E98: =G97*12%*C98/365 -> 29913.756 | F98: =D98+E98 -> 323422.4 | G98: =G97-D98 -> 2641577.7
B99: 46630 | C99: =B99-B98 -> 31 | D99: =105000-88.86+20796.82+167800.68 -> 293508.64 | E99: =G98*12%*C99/365 -> 26922.381 | F99: =D99+E99 -> 320431.02 | G99: =G98-D99 -> 2348069
B100: 46660 | C100: =B100-B99 -> 30 | D100: =105000-88.86+20796.82+167800.68 -> 293508.64 | E100: =G99*12%*C100/365 -> 23159.037 | F100: =D100+E100 -> 316667.68 | G100: =G99-D100 -> 2054560.4
B101: 46691 | C101: =B101-B100 -> 31 | D101: =105000-88.86+20796.82+167800.68 -> 293508.64 | E101: =G100*12%*C101/365 -> 20939.629 | F101: =D101+E101 -> 314448.27 | G101: =G100-D101 -> 1761051.7
B102: 46721 | C102: =B102-B101 -> 30 | D102: =105000-88.86+20796.82+167800.68 -> 293508.64 | E102: =G101*12%*C102/365 -> 17369.277 | F102: =D102+E102 -> 310877.92 | G102: =G101-D102 -> 1467543.1
B103: 46752 | C103: =B103-B102 -> 31 | D103: =105000-88.86+20796.82+167800.68 -> 293508.64 | E103: =G102*12%*C103/365 -> 14956.878 | F103: =D103+E103 -> 308465.52 | G103: =G102-D103 -> 1174034.5
...
